setup.py
Visual_Logging.egg-info/PKG-INFO
Visual_Logging.egg-info/SOURCES.txt
Visual_Logging.egg-info/dependency_links.txt
Visual_Logging.egg-info/top_level.txt
visual_logging.egg-info/SOURCES.txt
vlogging/__init__.py