Metadata-Version: 1.0
Name: visual-logging
Version: 0.1
Summary: A simple way to generate beautiful html logs with embedded images for CV purposes.
Home-page: https://github.com/dchaplinsky/visual-logging
Author: Dmitry Chaplinsky
Author-email: chaplinsky.dmitry@gmail.com
License: MIT
Platform: any
